<?xml version="1.0" encoding="utf-8"?>
<list>
  <config showall="true" notax="false" ignoreprice="false" keepenchanted="false" />
  <item id="1">
    <ingredient id="57" count="6000000" />
    <production id="547" count="1" />
  </item>
  <item id="2">
    <ingredient id="57" count="13000000" />
    <production id="2393" count="1" />
  </item>
  <item id="3">
    <ingredient id="57" count="6000000" />
    <production id="5769" count="1" />
  </item>
  <item id="4">
    <ingredient id="57" count="6000000" />
    <production id="5781" count="1" />
  </item>
  <item id="5">
    <ingredient id="57" count="6000000" />
    <production id="512" count="1" />
  </item>
  <item id="6">
    <ingredient id="57" count="7000000" />
    <production id="2385" count="1" />
  </item>
  <item id="7">
    <ingredient id="57" count="6000000" />
    <production id="2389" count="1" />
  </item>
  <item id="8">
    <ingredient id="57" count="6000000" />
    <production id="5766" count="1" />
  </item>
  <item id="9">
    <ingredient id="57" count="6000000" />
    <production id="5778" count="1" />
  </item>
  <item id="10">
    <ingredient id="57" count="6000000" />
    <production id="2418" count="1" />
  </item>
  <item id="11">
    <ingredient id="57" count="13000000" />
    <production id="2394" count="1" />
  </item>
  <item id="12">
    <ingredient id="57" count="6000000" />
    <production id="5772" count="1" />
  </item>
  <item id="13">
    <ingredient id="57" count="6000000" />
    <production id="5784" count="1" />
  </item>
  <item id="14">
    <ingredient id="57" count="6000000" />
    <production id="2419" count="1" />
  </item>
  <item id="15">
    <ingredient id="57" count="13000000" />
    <production id="2395" count="1" />
  </item>
  <item id="16">
    <ingredient id="57" count="6000000" />
    <production id="5775" count="1" />
  </item>
  <item id="17">
    <ingredient id="57" count="6000000" />
    <production id="5787" count="1" />
  </item>
  <item id="18">
    <ingredient id="57" count="10000000" />
    <production id="6382" count="1" />
  </item>
  <item id="19">
    <ingredient id="57" count="15000000" />
    <production id="6379" count="1" />
  </item>
  <item id="20">
    <ingredient id="57" count="10000000" />
    <production id="6380" count="1" />
  </item>
  <item id="21">
    <ingredient id="57" count="10000000" />
    <production id="6381" count="1" />
  </item>
  <item id="22">
    <ingredient id="57" count="15000000" />
    <production id="9429" count="1" />
  </item>
  <item id="23">
    <ingredient id="57" count="18000000" /> 
    <production id="9425" count="1" />
  </item>
  <item id="24">
    <ingredient id="57" count="20000000" />
    <production id="9426" count="1" />
  </item>
  <item id="25">
    <ingredient id="57" count="20000000" />
    <production id="9427" count="1" />
  </item>
  <item id="26">
    <ingredient id="57" count="20000000" />
    <production id="10126" count="1" />
  </item>
  <item id="27">
    <ingredient id="57" count="20000000" />
    <production id="10127" count="1" />
  </item>
  <item id="28">
    <ingredient id="57" count="20000000" />
    <production id="10168" count="1" />
  </item>
  <item id="29">
    <ingredient id="57" count="20000000" />
    <production id="10214" count="1" />
  </item>
  <item id="30">
    <ingredient id="57" count="15000000" />
    <production id="9428" count="1" />
  </item>
  <item id="31">
    <ingredient id="57" count="15000000" />
    <production id="9430" count="1" />
  </item>
  <item id="32">
    <ingredient id="57" count="15000000" />
    <production id="9431" count="1" />
  </item>
  <item id="40">
    <ingredient id="4356" count="125" />
    <production id="15607" count="1" />
  </item>
  <item id="41">
    <ingredient id="4356" count="140" />
    <production id="15610" count="1" />
  </item>
  <item id="42">
    <ingredient id="4356" count="125" />
    <production id="15613" count="1" />
  </item>
  <item id="43">
    <ingredient id="4356" count="110" />
    <production id="15616" count="1" />
  </item>
  <item id="44">
    <ingredient id="4356" count="110" />
    <production id="15619" count="1" />
  </item>
</list>